metalgpy/__init__.py
metalgpy/__version__.py
metalgpy/_decorator.py
metalgpy/_expression.py
metalgpy/_sample.py
metalgpy/_skopt.py
metalgpy/constraints/__init__.py
metalgpy/optimizer/__init__.py
metalgpy/optimizer/_base_optimizer.py
metalgpy/optimizer/skopt/__init__.py
metalgpy/optimizer/skopt/acquisition.py
metalgpy/optimizer/skopt/benchmarks.py
metalgpy/optimizer/skopt/callbacks.py
metalgpy/optimizer/skopt/plots.py
metalgpy/optimizer/skopt/searchcv.py
metalgpy/optimizer/skopt/utils.py
metalgpy/optimizer/skopt/learning/__init__.py
metalgpy/optimizer/skopt/learning/forest.py
metalgpy/optimizer/skopt/learning/gbrt.py
metalgpy/optimizer/skopt/learning/gaussian_process/__init__.py
metalgpy/optimizer/skopt/learning/gaussian_process/gpr.py
metalgpy/optimizer/skopt/learning/gaussian_process/kernels.py
metalgpy/optimizer/skopt/learning/gaussian_process/tests/__init__.py
metalgpy/optimizer/skopt/learning/gaussian_process/tests/test_gpr.py
metalgpy/optimizer/skopt/learning/gaussian_process/tests/test_kernels.py
metalgpy/optimizer/skopt/learning/tests/__init__.py
metalgpy/optimizer/skopt/learning/tests/test_forest.py
metalgpy/optimizer/skopt/learning/tests/test_gbrt.py
metalgpy/optimizer/skopt/optimizer/__init__.py
metalgpy/optimizer/skopt/optimizer/base.py
metalgpy/optimizer/skopt/optimizer/dummy.py
metalgpy/optimizer/skopt/optimizer/forest.py
metalgpy/optimizer/skopt/optimizer/gbrt.py
metalgpy/optimizer/skopt/optimizer/gp.py
metalgpy/optimizer/skopt/optimizer/optimizer.py
metalgpy/optimizer/skopt/optimizer/utils.py
metalgpy/optimizer/skopt/sampler/__init__.py
metalgpy/optimizer/skopt/sampler/base.py
metalgpy/optimizer/skopt/sampler/grid.py
metalgpy/optimizer/skopt/sampler/halton.py
metalgpy/optimizer/skopt/sampler/hammersly.py
metalgpy/optimizer/skopt/sampler/lhs.py
metalgpy/optimizer/skopt/sampler/sobol.py
metalgpy/optimizer/skopt/space/__init__.py
metalgpy/optimizer/skopt/space/space.py
metalgpy/optimizer/skopt/space/transformers.py
metalgpy/sampler/__init__.py
metalgpy-0.0.2.dist-info/LICENSE
metalgpy-0.0.2.dist-info/METADATA
metalgpy-0.0.2.dist-info/WHEEL
metalgpy-0.0.2.dist-info/top_level.txt
metalgpy-0.0.2.dist-info/RECORD
