Metadata-Version: 2.1
Name: metalgpy
Version: 0.0.2
Summary: Describe and manipulate programs as Meta-Algorithms in Python.
Home-page: https://github.com/deephyper/metalgpy
Author: Romain Egele <romainegele@gmail.com>
Maintainer: Romain Egele
Maintainer-email: romainegele@gmail.com
License: BSD 2-Clause "Simplified" License
Project-URL: Changes, https://github.com/deephyper/metalgpy/releases
Project-URL: Source Code, https://github.com/deephyper/metalgpy
Project-URL: Issue Tracker, https://github.com/deephyper/metalgpy/issues
Project-URL: Discussion, https://github.com/deephyper/metalgpy/discussions
Classifier: Development Status :: 3 - Alpha
Classifier: Programming Language :: Python
Classifier: Programming Language :: Python :: 3
Classifier: Programming Language :: Python :: 3.7
Classifier: Programming Language :: Python :: 3.8
Classifier: Programming Language :: Python :: 3.9
Requires-Python: >=3.7
License-File: LICENSE
Requires-Dist: dm-tree
Requires-Dist: numpy
Requires-Dist: scipy
Requires-Dist: pandas
Requires-Dist: scikit-learn
Requires-Dist: packaging
Requires-Dist: pyyaml
Provides-Extra: dev
Requires-Dist: twine ; extra == 'dev'
Requires-Dist: black ; extra == 'dev'
